README.rst
setup.cfg
setup.py
jzqt/__init__.py
jzqt/containers.py
jzqt/importools.py
jzqt/timetools.py
jzqt.egg-info/PKG-INFO
jzqt.egg-info/SOURCES.txt
jzqt.egg-info/dependency_links.txt
jzqt.egg-info/top_level.txt